Metadata-Version: 2.1
Name: mass-extinction
Version: 1.0.0
Summary: Mass extinction class for evolutionary algorithms.
Home-page: https://bitbucket.org/Trench58/mass_extinction/src/master/
Author: Kaelan Engholdt
Author-email: extinctionpackage@gmail.com
License: UNKNOWN
Keywords: extinction evolutionary genetic algorithm
Platform: UNKNOWN
Classifier: Development Status :: 5 - Production/Stable
Classifier: Intended Audience :: Science/Research
Classifier: License :: OSI Approved :: MIT License
Classifier: Natural Language :: English
Classifier: Operating System :: OS Independent
Classifier: Programming Language :: Python
Classifier: Topic :: Scientific/Engineering :: Artificial Intelligence
Classifier: Topic :: Scientific/Engineering :: Artificial Life
